iotexapi/__init__.py
iotexapi/constants.py
iotexapi/iotx.py
iotexapi/main.py
iotexapi/module.py
iotexapi/utils.py
iotexapi/common/__init__.py
iotexapi/common/account.py
iotexapi/common/datastructures.py
iotexapi/common/formatters.py
iotexapi/common/toolz/__init__.py
iotexapi/proto/__init__.py
iotexapi/proto/api/__init__.py
iotexapi/proto/api/api_pb2.py
iotexapi/proto/api/api_pb2_grpc.py
iotexapi/proto/rpc/__init__.py
iotexapi/proto/rpc/rpc_pb2.py
iotexapi/proto/testing/__init__.py
iotexapi/proto/testing/testing_pb2.py
iotexapi/proto/types/__init__.py
iotexapi/proto/types/action_pb2.py
iotexapi/proto/types/blockchain_pb2.py
iotexapi/proto/types/consensus_pb2.py
iotexapi/proto/types/endorsement_pb2.py
iotexapi/proto/types/genesis_pb2.py
iotexapi/proto/types/node_pb2.py
iotexapi-0.0.1.dist-info/METADATA
iotexapi-0.0.1.dist-info/WHEEL
iotexapi-0.0.1.dist-info/top_level.txt
iotexapi-0.0.1.dist-info/RECORD
